tester_alice_skill_flask/__init__.py
tester_alice_skill_flask-1.1.dist-info/LICENSE
tester_alice_skill_flask-1.1.dist-info/METADATA
tester_alice_skill_flask-1.1.dist-info/WHEEL
tester_alice_skill_flask-1.1.dist-info/top_level.txt
tester_alice_skill_flask-1.1.dist-info/RECORD
